openscadbase-0.1.2.dist-info/METADATA
openscadbase-0.1.2.dist-info/WHEEL
openscadbase-0.1.2.dist-info/entry_points.txt
openscadbase/__init__.py
openscadbase/base.py
openscadbase/elements.py
openscadbase/operations.py
openscadbase/py.typed
openscadbase/transformations.py
openscadbase-0.1.2.dist-info/RECORD
