Metadata-Version: 2.1
Name: openscadbase
Version: 0.1.2
Summary: use open scad primitives from python to compose documents.
License: MIT
Requires-Python: >=3.11
